djscoe/__init__.py
djscoe/ai.py
djscoe/cn.py
djscoe/daa.py
djscoe/de.py
djscoe/dsa.py
djscoe/os.py
djscoe/poa.py
djscoe/python.py
djscoe-0.0.5.dist-info/licenses/LICENSE
djscoe-0.0.5.dist-info/METADATA
djscoe-0.0.5.dist-info/WHEEL
djscoe-0.0.5.dist-info/top_level.txt
djscoe-0.0.5.dist-info/RECORD
