Metadata-Version: 2.4
Name: djscoe
Version: 0.0.5
Summary: DJSCE
Home-page: 
Author: Mihir Panchal
Author-email: mihirpanchal5400@gmail.com
License: MIT
Keywords: djscoe
Classifier: Development Status :: 5 - Production/Stable
Classifier: Intended Audience :: Education
Classifier: Operating System :: Microsoft :: Windows :: Windows 10
Classifier: License :: OSI Approved :: MIT License
Classifier: Programming Language :: Python :: 3
License-File: LICENSE
Dynamic: author
Dynamic: author-email
Dynamic: classifier
Dynamic: description
Dynamic: keywords
Dynamic: license
Dynamic: license-file
Dynamic: summary
